<?xml version="1.0" encoding="UTF-8"?>
<office:document-meta xmlns:meta="urn:oasis:names:tc:opendocument:xmlns:meta:1.0" xmlns:office="urn:oasis:names:tc:opendocument:xmlns:office:1.0" xmlns:grddl="http://www.w3.org/2003/g/data-view#" xmlns:ooo="http://openoffice.org/2004/office" xmlns:xlink="http://www.w3.org/1999/xlink" xmlns:dc="http://purl.org/dc/elements/1.1/" office:version="1.2"><office:meta><meta:generator>LibreOffice/6.3.6.2$Windows_X86_64 LibreOffice_project/2196df99b074d8a661f4036fca8fa0cbfa33a497</meta:generator><dc:date>2020-06-09T15:24:22.262000000</dc:date><meta:editing-duration>PT37S</meta:editing-duration><meta:editing-cycles>1</meta:editing-cycles><meta:document-statistic meta:table-count="0" meta:image-count="0" meta:object-count="0" meta:page-count="188" meta:paragraph-count="5930" meta:word-count="101472" meta:character-count="635632" meta:non-whitespace-character-count="540060"/></office:meta></office:document-meta>